askjson/__init__.py
askjson/utils.py
askjson/__pycache__/__init__.cpython-38.pyc
askjson/__pycache__/utils.cpython-38.pyc
AskJSON-0.1.2.dist-info/LICENSE
AskJSON-0.1.2.dist-info/METADATA
AskJSON-0.1.2.dist-info/WHEEL
AskJSON-0.1.2.dist-info/top_level.txt
AskJSON-0.1.2.dist-info/RECORD
