Metadata-Version: 2.1
Name: AskJSON
Version: 0.1.2
Summary: A library to ask questions to JSON data and get Python code in response.
Home-page: https://github.com/somnath6646/AskJSON
Author: Somnath
Author-email: somnathmishra6646@gmail.com
Project-URL: Bug Tracker, https://github.com/Somnath6646/AskJSON/issues
Project-URL: Documentation, https://github.com/Somnath6646/AskJSON#readme
Project-URL: Source Code, https://github.com/Somnath6646/AskJSON
Keywords: json query ai openai python code generation
Classifier: Programming Language :: Python :: 3
Classifier: License :: OSI Approved :: MIT License
Classifier: Operating System :: OS Independent
Classifier: Intended Audience :: Developers
Classifier: Topic :: Software Development :: Libraries :: Python Modules
Classifier: Topic :: Utilities
Requires-Python: >=3.6
License-File: LICENSE
Requires-Dist: openai
Requires-Dist: termcolor
Requires-Dist: python-dotenv
Requires-Dist: stdlib-list
